{
	"斧術熟練+10%": {
		"title": "斧術熟練+10%",
		"description": "§c必要ポイント1",
		"size": 1,
		"icon": {
			"type": "item",
			"data": {
				"item": "minecraft:iron_axe"
			}
		},
		"frame": {
			"type": "advancement",
			"data": {
				"frame": "task"
			}
		},
		"rewards": [
			{
				"type": "puffish_skills:attribute",
				"data": {
					"attribute": "puffish_attributes:axe_damage",
					"value": 0.1,
					"operation": "multiply_base"
				}
			}
		],
		"cost": 1,
		"metadata": {
			"icon": "elxacvbto7dkkqp7"
		}
	},
	"三叉槍熟練+10%": {
		"title": "三叉槍熟練+10%",
		"description": "§c必要ポイント1",
		"size": 1,
		"icon": {
			"type": "item",
			"data": {
				"item": "minecraft:trident"
			}
		},
		"frame": {
			"type": "advancement",
			"data": {
				"frame": "task"
			}
		},
		"rewards": [
			{
				"type": "puffish_skills:attribute",
				"data": {
					"attribute": "puffish_attributes:trident_damage",
					"value": 0.1,
					"operation": "multiply_base"
				}
			}
		],
		"cost": 1,
		"metadata": {
			"icon": "6mf5xxn0hv46bkwp"
		}
	},
	"メイス熟練+10%": {
		"title": "メイス熟練+10%",
		"description": "§c必要ポイント1",
		"size": 1,
		"icon": {
			"type": "item",
			"data": {
				"item": "minecraft:mace"
			}
		},
		"frame": {
			"type": "advancement",
			"data": {
				"frame": "task"
			}
		},
		"rewards": [
			{
				"type": "puffish_skills:attribute",
				"data": {
					"attribute": "puffish_attributes:mace_damage",
					"value": 0.1,
					"operation": "multiply_base"
				}
			}
		],
		"cost": 1,
		"metadata": {
			"icon": "isr1bynwh7fjb3a8"
		}
	},
	"攻撃速度+5%": {
		"title": "攻撃速度+5%",
		"description": "§c必要ポイント1",
		"size": 1,
		"icon": {
			"type": "effect",
			"data": {
				"effect": "minecraft:strength"
			}
		},
		"frame": {
			"type": "advancement",
			"data": {
				"frame": "task"
			}
		},
		"rewards": [
			{
				"type": "puffish_skills:attribute",
				"data": {
					"attribute": "attack_speed",
					"value": 0.05,
					"operation": "multiply_total"
				}
			}
		],
		"cost": 1,
		"metadata": {
			"icon": "bls99mt177comkjx"
		}
	},
	"体力+1": {
		"title": "体力+1",
		"description": "§c必要ポイント2",
		"icon": {
			"type": "effect",
			"data": {
				"effect": "minecraft:health_boost"
			}
		},
		"rewards": [
			{
				"type": "puffish_skills:attribute",
				"data": {
					"attribute": "max_health",
					"value": 2,
					"operation": "addition"
				}
			}
		],
		"cost": 2,
		"metadata": {
			"icon": "d9ytvbgbmdcr3ycc"
		}
	},
	"吸血+5%": {
		"title": "吸血+5%",
		"description": "§c必要ポイント2",
		"size": 1,
		"icon": {
			"type": "item",
			"data": {
				"item": "minecraft:spider_eye"
			}
		},
		"frame": {
			"type": "advancement",
			"data": {
				"frame": "task"
			}
		},
		"rewards": [
			{
				"type": "puffish_skills:attribute",
				"data": {
					"attribute": "puffish_attributes:life_steal",
					"value": 0.05,
					"operation": "addition"
				}
			}
		],
		"cost": 2,
		"metadata": {
			"icon": "f23dw1bs4x56yoeq"
		}
	},
	"全耐性無視+1.0": {
		"title": "全耐性無視+1.0",
		"description": "§c必要ポイント2",
		"size": 1,
		"icon": {
			"type": "item",
			"data": {
				"item": "minecraft:netherite_scrap"
			}
		},
		"frame": {
			"type": "advancement",
			"data": {
				"frame": "task"
			}
		},
		"rewards": [
			{
				"type": "puffish_skills:attribute",
				"data": {
					"attribute": "puffish_attributes:resistance_shred",
					"value": 1.0,
					"operation": "multiply_base"
				}
			}
		],
		"cost": 2,
		"metadata": {
			"icon": "1tmb23xzmzuev85e"
		}
	},
	"軽減エンチャント無視+1.0": {
		"title": "軽減エンチャント無視+1.0",
		"description": "§c必要ポイント3",
		"size": 1,
		"icon": {
			"type": "item",
			"data": {
				"item": "minecraft:enchanted_book"
			}
		},
		"frame": {
			"type": "advancement",
			"data": {
				"frame": "task"
			}
		},
		"rewards": [
			{
				"type": "puffish_skills:attribute",
				"data": {
					"attribute": "puffish_attributes:protection_shred",
					"value": 1.0,
					"operation": "multiply_base"
				}
			}
		],
		"cost": 3,
		"metadata": {
			"icon": "d8tlxqw08l3srqun"
		}
	},
	"自然治癒+10%": {
		"title": "自然治癒+10%",
		"description": "§c必要ポイント1",
		"size": 1,
		"icon": {
			"type": "effect",
			"data": {
				"effect": "minecraft:instant_health"
			}
		},
		"frame": {
			"type": "advancement",
			"data": {
				"frame": "task"
			}
		},
		"rewards": [
			{
				"type": "puffish_skills:attribute",
				"data": {
					"attribute": "puffish_attributes:natural_regeneration",
					"value": 0.1,
					"operation": "multiply_base"
				}
			}
		],
		"cost": 1,
		"metadata": {
			"icon": "tmcfsnw2hc2giqpn"
		}
	},
	"治癒力向上+10%": {
		"title": "治癒力向上+10%",
		"description": "§c必要ポイント1",
		"size": 1,
		"icon": {
			"type": "effect",
			"data": {
				"effect": "minecraft:regeneration"
			}
		},
		"frame": {
			"type": "advancement",
			"data": {
				"frame": "task"
			}
		},
		"rewards": [
			{
				"type": "puffish_skills:attribute",
				"data": {
					"attribute": "puffish_attributes:healing",
					"value": 0.1,
					"operation": "multiply_base"
				}
			}
		],
		"cost": 1,
		"metadata": {
			"icon": "my6zoa38jvtksqbo"
		}
	},
	"隠密+1.0": {
		"title": "隠密+1.0",
		"description": "§c必要ポイント1",
		"size": 1,
		"icon": {
			"type": "item",
			"data": {
				"item": "minecraft:black_dye"
			}
		},
		"frame": {
			"type": "advancement",
			"data": {
				"frame": "task"
			}
		},
		"rewards": [
			{
				"type": "puffish_skills:attribute",
				"data": {
					"attribute": "puffish_attributes:stealth",
					"value": 1,
					"operation": "addition"
				}
			}
		],
		"cost": 1,
		"metadata": {
			"icon": "5ab3ryv6lbi2hs1f"
		}
	},
	"幸運+0.25": {
		"title": "幸運+0.25",
		"description": "§c必要ポイント4",
		"size": 1,
		"icon": {
			"type": "effect",
			"data": {
				"effect": "luck"
			}
		},
		"frame": {
			"type": "advancement",
			"data": {
				"frame": "task"
			}
		},
		"rewards": [
			{
				"type": "puffish_skills:attribute",
				"data": {
					"attribute": "puffish_attributes:fortune",
					"value": 0.25,
					"operation": "addition"
				}
			}
		],
		"cost": 4,
		"metadata": {
			"icon": "lr8rtyl6w95d68qx"
		}
	},
	"運+0.25": {
		"title": "運+0.25",
		"description": "§c必要ポイント4",
		"icon": {
			"type": "effect",
			"data": {
				"effect": "luck"
			}
		},
		"rewards": [
			{
				"type": "puffish_skills:attribute",
				"data": {
					"attribute": "luck",
					"value": 0.25,
					"operation": "addition"
				}
			}
		],
		"cost": 4,
		"metadata": {
			"icon": "1sntmopyco2dmgx9"
		}
	},
	"使役獣攻撃力+10%": {
		"title": "使役獣攻撃力+10%",
		"description": "§c必要ポイント1",
		"size": 1,
		"icon": {
			"type": "item",
			"data": {
				"item": "minecraft:bone"
			}
		},
		"frame": {
			"type": "advancement",
			"data": {
				"frame": "task"
			}
		},
		"rewards": [
			{
				"type": "puffish_skills:attribute",
				"data": {
					"attribute": "puffish_attributes:tamed_damage",
					"value": 0.1,
					"operation": "multiply_base"
				}
			}
		],
		"cost": 1,
		"metadata": {
			"icon": "5ptyqzt7esqlog0f"
		}
	},
	"使役獣耐性+10%": {
		"title": "使役獣耐性+10%",
		"description": "§c必要ポイント2",
		"size": 1,
		"icon": {
			"type": "item",
			"data": {
				"item": "minecraft:wolf_armor"
			}
		},
		"frame": {
			"type": "advancement",
			"data": {
				"frame": "task"
			}
		},
		"rewards": [
			{
				"type": "puffish_skills:attribute",
				"data": {
					"attribute": "puffish_attributes:tamed_resistance",
					"value": 0.1,
					"operation": "addition"
				}
			}
		],
		"cost": 2,
		"metadata": {
			"icon": "sdlyuurqv488cwwk"
		}
	},
	"騎乗物速度+10%": {
		"title": "騎乗物速度+10%",
		"description": "§c必要ポイント1",
		"size": 1,
		"icon": {
			"type": "item",
			"data": {
				"item": "minecraft:saddle"
			}
		},
		"frame": {
			"type": "advancement",
			"data": {
				"frame": "task"
			}
		},
		"rewards": [
			{
				"type": "puffish_skills:attribute",
				"data": {
					"attribute": "puffish_attributes:mount_speed",
					"value": 0.1,
					"operation": "multiply_base"
				}
			}
		],
		"cost": 1,
		"metadata": {
			"icon": "ykj4t9udgba3aght"
		}
	},
	"剣術熟練+10%": {
		"title": "剣術熟練+10%",
		"description": "§c必要ポイント1",
		"size": 1,
		"icon": {
			"type": "item",
			"data": {
				"item": "minecraft:stone_sword"
			}
		},
		"frame": {
			"type": "advancement",
			"data": {
				"frame": "task"
			}
		},
		"rewards": [
			{
				"type": "puffish_skills:attribute",
				"data": {
					"attribute": "puffish_attributes:sword_damage",
					"value": 0.1,
					"operation": "multiply_base"
				}
			}
		],
		"cost": 1,
		"metadata": {
			"icon": "m0b6g8o6o7mcu001"
		}
	},
	"近接攻撃力+10%": {
		"title": "近接攻撃力+10%",
		"description": "§c必要ポイント1",
		"size": 1,
		"icon": {
			"type": "item",
			"data": {
				"item": "minecraft:iron_sword"
			}
		},
		"frame": {
			"type": "advancement",
			"data": {
				"frame": "task"
			}
		},
		"rewards": [
			{
				"type": "puffish_skills:attribute",
				"data": {
					"attribute": "puffish_attributes:melee_damage",
					"value": 0.1,
					"operation": "multiply_base"
				}
			}
		],
		"cost": 1,
		"metadata": {
			"icon": "skkxpe0nloanfgxh"
		}
	},
	"ノックバック強化+0.2": {
		"title": "ノックバック強化+0.2",
		"description": "§c必要ポイント2",
		"size": 1,
		"icon": {
			"type": "item",
			"data": {
				"item": "minecraft:piston"
			}
		},
		"frame": {
			"type": "advancement",
			"data": {
				"frame": "task"
			}
		},
		"rewards": [
			{
				"type": "puffish_skills:attribute",
				"data": {
					"attribute": "puffish_attributes:knockback",
					"value": 0.2,
					"operation": "addition"
				}
			}
		],
		"cost": 2,
		"metadata": {
			"icon": "bxgnpb1tqasbxu08"
		}
	},
	"近接耐性+10%": {
		"title": "近接耐性+10%",
		"description": "§c必要ポイント2",
		"size": 1,
		"icon": {
			"type": "item",
			"data": {
				"item": "minecraft:shield"
			}
		},
		"frame": {
			"type": "advancement",
			"data": {
				"frame": "task"
			}
		},
		"rewards": [
			{
				"type": "puffish_skills:attribute",
				"data": {
					"attribute": "puffish_attributes:melee_resistance",
					"value": 0.1,
					"operation": "addition"
				}
			}
		],
		"cost": 2,
		"metadata": {
			"icon": "je16qa8h0dsmurnk"
		}
		},
	"近接耐性無視+1.0": {
		"title": "近接耐性無視+1.0",
		"description": "§c必要ポイント2",
		"size": 1,
		"icon": {
			"type": "item",
			"data": {
				"item": "minecraft:flint"
			}
		},
		"frame": {
			"type": "advancement",
			"data": {
				"frame": "task"
			}
		},
		"rewards": [
			{
				"type": "puffish_skills:attribute",
				"data": {
					"attribute": "puffish_attributes:melee_resistance_shred",
					"value": 1.0,
					"operation": "multiply_base"
				}
			}
		],
		"cost": 2,
		"metadata": {
			"icon": "jwsous23ukvo1bf5"
		}
	},
	"射撃攻撃力+5%": {
		"title": "射撃攻撃力+5%",
		"description": "§c必要ポイント1",
		"size": 1,
		"icon": {
			"type": "item",
			"data": {
				"item": "minecraft:bow"
			}
		},
		"frame": {
			"type": "advancement",
			"data": {
				"frame": "task"
			}
		},
		"rewards": [
			{
				"type": "puffish_skills:attribute",
				"data": {
					"attribute": "puffish_attributes:ranged_damage",
					"value": 0.05,
					"operation": "multiply_base"
				}
			}
		],
		"cost": 1,
		"metadata": {
			"icon": "lwx9birx79vtdf9h"
		}
	},
	"弾速+5%": {
		"title": "弾速+5%",
		"description": "§c必要ポイント1",
		"size": 1,
		"icon": {
			"type": "item",
			"data": {
				"item": "minecraft:arrow"
			}
		},
		"frame": {
			"type": "advancement",
			"data": {
				"frame": "task"
			}
		},
		"rewards": [
			{
				"type": "puffish_skills:attribute",
				"data": {
					"attribute": "puffish_attributes:bow_projectile_speed",
					"value": 0.5,
					"operation": "multiply_total"
				}
			},
			{
				"type": "puffish_skills:attribute",
				"data": {
					"attribute": "puffish_attributes:crossbow_projectile_speed",
					"value": 0.5,
					"operation": "multiply_total"
				}
			}
		],
		"cost": 1,
		"metadata": {
			"icon": "29v4eqr4077k97f3"
		}
	},
	"射撃耐性+10%": {
		"title": "射撃耐性+10%",
		"description": "§c必要ポイント2",
		"size": 1,
		"icon": {
			"type": "item",
			"data": {
				"item": "minecraft:chainmail_chestplate"
			}
		},
		"frame": {
			"type": "advancement",
			"data": {
				"frame": "task"
			}
		},
		"rewards": [
			{
				"type": "puffish_skills:attribute",
				"data": {
					"attribute": "puffish_attributes:ranged_resistance",
					"value": 0.1,
					"operation": "addition"
				}
			}
		],
		"cost": 2,
		"metadata": {
			"icon": "8bakzigruqqb89kk"
		}
	},
	"射撃耐性無視+1.0": {
		"title": "射撃耐性無視+1.0",
		"description": "§c必要ポイント2",
		"size": 1,
		"icon": {
			"type": "item",
			"data": {
				"item": "minecraft:crossbow"
			}
		},
		"frame": {
			"type": "advancement",
			"data": {
				"frame": "task"
			}
		},
		"rewards": [
			{
				"type": "puffish_skills:attribute",
				"data": {
					"attribute": "puffish_attributes:ranged_resistance_shred",
					"value": 1.0,
					"operation": "multiply_base"
				}
			}
		],
		"cost": 2,
		"metadata": {
			"icon": "06yzfbmtp6wagtur"
		}
	},
	"防御力+0.5": {
		"title": "防御力+0.5",
		"description": "§c必要ポイント2",
		"size": 1,
		"icon": {
			"type": "item",
			"data": {
				"item": "minecraft:iron_chestplate"
			}
		},
		"frame": {
			"type": "advancement",
			"data": {
				"frame": "task"
			}
		},
		"rewards": [
			{
				"type": "puffish_skills:attribute",
				"data": {
					"attribute": "minecraft:armor",
					"value": 1,
					"operation": "addition"
				}
			}
		],
		"cost": 2,
		"metadata": {
			"icon": "oh78cxcetyvv3c2x"
		}
	},
	"ダメージ反射+10%": {
		"title": "ダメージ反射+10%",
		"description": "§c必要ポイント1",
		"size": 1,
		"icon": {
			"type": "effect",
			"data": {
				"effect": "minecraft:absorption"
			}
		},
		"frame": {
			"type": "advancement",
			"data": {
				"frame": "task"
			}
		},
		"rewards": [
			{
				"type": "puffish_skills:attribute",
				"data": {
					"attribute": "puffish_attributes:damage_reflection",
					"value": 0.1,
					"operation": "addition"
				}
			}
		],
		"cost": 1,
		"metadata": {
			"icon": "w1910b75yxr3ghoy"
		}
	},
	"耐性+5%": {
		"title": "耐性+5%",
		"description": "§c必要ポイント2",
		"size": 1,
		"icon": {
			"type": "effect",
			"data": {
				"effect": "minecraft:resistance"
			}
		},
		"frame": {
			"type": "advancement",
			"data": {
				"frame": "task"
			}
		},
		"rewards": [
			{
				"type": "puffish_skills:attribute",
				"data": {
					"attribute": "puffish_attributes:resistance",
					"value": 0.05,
					"operation": "addition"
				}
			}
		],
		"cost": 2,
		"metadata": {
			"icon": "27en5gyceirp2jr6"
		}
	},
	"防御無視+1.0": {
		"title": "防御無視+1.0",
		"description": "§c必要ポイント2",
		"size": 1,
		"icon": {
			"type": "item",
			"data": {
				"item": "minecraft:flint"
			}
		},
		"frame": {
			"type": "advancement",
			"data": {
				"frame": "task"
			}
		},
		"rewards": [
			{
				"type": "puffish_skills:attribute",
				"data": {
					"attribute": "puffish_attributes:armor_shred",
					"value": 1.0,
					"operation": "multiply_base"
				}
			}
		],
		"cost": 2,
		"metadata": {
			"icon": "euu5zmzluor6o5e1"
		}
	},
	"防具強度無視+1.0": {
		"title": "防具強度無視+1.0",
		"description": "§c必要ポイント2",
		"size": 1,
		"icon": {
			"type": "item",
			"data": {
				"item": "minecraft:flint"
			}
		},
		"frame": {
			"type": "advancement",
			"data": {
				"frame": "task"
			}
		},
		"rewards": [
			{
				"type": "puffish_skills:attribute",
				"data": {
					"attribute": "puffish_attributes:toughness_shred",
					"value": 1.0,
					"operation": "multiply_base"
				}
			}
		],
		"cost": 2,
		"metadata": {
			"icon": "j32kxx3mp8g1acvo"
		}
	},
	"ポーション攻撃力+10%": {
		"title": "ポーション攻撃力+10%",
		"description": "§c必要ポイント1",
		"size": 1,
		"icon": {
			"type": "item",
			"data": {
				"item": "minecraft:potion"
			}
		},
		"frame": {
			"type": "advancement",
			"data": {
				"frame": "task"
			}
		},
		"rewards": [
			{
				"type": "puffish_skills:attribute",
				"data": {
					"attribute": "puffish_attributes:magic_damage",
					"value": 0.1,
					"operation": "multiply_base"
				}
			}
		],
		"cost": 1,
		"metadata": {
			"icon": "z6bnawh6qo2iz2ui"
		}
	},
	"ポーション耐性+10%": {
		"title": "ポーション耐性+10%",
		"description": "§c必要ポイント2",
		"size": 1,
		"icon": {
			"type": "item",
			"data": {
				"item": "minecraft:amethyst_shard"
			}
		},
		"frame": {
			"type": "advancement",
			"data": {
				"frame": "task"
			}
		},
		"rewards": [
			{
				"type": "puffish_skills:attribute",
				"data": {
					"attribute": "puffish_attributes:magic_resistance",
					"value": 0.1,
					"operation": "addition"
				}
			}
		],
		"cost": 2,
		"metadata": {
			"icon": "i0w7vlz5n1w5wfva"
		}
	},
	"ポーション耐性無視+1.0": {
		"title": "ポーション耐性無視+1.0",
		"description": "§c必要ポイント2",
		"size": 1,
		"icon": {
			"type": "item",
			"data": {
				"item": "minecraft:amethyst_cluster"
			}
		},
		"frame": {
			"type": "advancement",
			"data": {
				"frame": "task"
			}
		},
		"rewards": [
			{
				"type": "puffish_skills:attribute",
				"data": {
					"attribute": "puffish_attributes:magic_resistance_shred",
					"value": 1.0,
					"operation": "multiply_base"
				}
			}
		],
		"cost": 2,
		"metadata": {
			"icon": "9lgmf7umtzktkvib"
		}
	},
	"アックス速度+10%": {
		"title": "アックス速度+10%",
		"description": "§c必要ポイント1",
		"size": 1,
		"icon": {
			"type": "item",
			"data": {
				"item": "minecraft:golden_axe"
			}
		},
		"frame": {
			"type": "advancement",
			"data": {
				"frame": "task"
			}
		},
		"rewards": [
			{
				"type": "puffish_skills:attribute",
				"data": {
					"attribute": "puffish_attributes:axe_speed",
					"value": 0.1,
					"operation": "multiply_total"
				}
			}
		],
		"cost": 1,
		"metadata": {
			"icon": "m8xif69cktymemyz"
		}
	},
	"シャベル速度+10%": {
		"title": "シャベル速度+10%",
		"description": "§c必要ポイント1",
		"size": 1,
		"icon": {
			"type": "item",
			"data": {
				"item": "minecraft:golden_shovel"
			}
		},
		"frame": {
			"type": "advancement",
			"data": {
				"frame": "task"
			}
		},
		"rewards": [
			{
				"type": "puffish_skills:attribute",
				"data": {
					"attribute": "puffish_attributes:shovel_speed",
					"value": 0.1,
					"operation": "multiply_total"
				}
			}
		],
		"cost": 1,
		"metadata": {
			"icon": "3pvph6sowbg6kvq6"
		}
	},
	"ツルハシ速度+10%": {
		"title": "ツルハシ速度+10%",
		"description": "§c必要ポイント1",
		"size": 1,
		"icon": {
			"type": "item",
			"data": {
				"item": "minecraft:golden_pickaxe"
			}
		},
		"frame": {
			"type": "advancement",
			"data": {
				"frame": "task"
			}
		},
		"rewards": [
			{
				"type": "puffish_skills:attribute",
				"data": {
					"attribute": "puffish_attributes:pickaxe_speed",
					"value": 0.1,
					"operation": "multiply_base"
				}
			}
		],
		"cost": 1,
		"metadata": {
			"icon": "1zlofbr8tof1rh65"
		}
	},
	"採掘速度+10%": {
		"title": "採掘速度+10%",
		"description": "§c必要ポイント2",
		"size": 1,
		"icon": {
			"type": "effect",
			"data": {
				"effect": "minecraft:haste"
			}
		},
		"frame": {
			"type": "advancement",
			"data": {
				"frame": "task"
			}
		},
		"rewards": [
			{
				"type": "puffish_skills:attribute",
				"data": {
					"attribute": "puffish_attributes:mining_speed",
					"value": 0.1,
					"operation": "multiply_base"
				}
			}
		],
		"cost": 2,
		"metadata": {
			"icon": "lunnx3twjqlssqgo"
		}
	},
	"破壊速度+10%": {
		"title": "破壊速度+10%",
		"description": "§c必要ポイント2",
		"size": 1,
		"icon": {
			"type": "item",
			"data": {
				"item": "minecraft:netherite_pickaxe"
			}
		},
		"frame": {
			"type": "advancement",
			"data": {
				"frame": "task"
			}
		},
		"rewards": [
			{
				"type": "puffish_skills:attribute",
				"data": {
					"attribute": "puffish_attributes:breaking_speed",
					"value": 0.1,
					"operation": "multiply_base"
				}
			}
		],
		"cost": 2,
		"metadata": {
			"icon": "zwbeiowvto9a0289"
		}
	},
	"食事速度+10%": {
		"title": "食事速度+10%",
		"description": "§c必要ポイント1",
		"size": 1,
		"icon": {
			"type": "item",
			"data": {
				"item": "minecraft:cooked_beef"
			}
		},
		"frame": {
			"type": "advancement",
			"data": {
				"frame": "task"
			}
		},
		"rewards": [
			{
				"type": "puffish_skills:attribute",
				"data": {
					"attribute": "puffish_attributes:consuming_speed",
					"value": 0.1,
					"operation": "multiply_base"
				}
			}
		],
		"cost": 1,
		"metadata": {
			"icon": "tiy6se7hvurdrk2v"
		}
	},
	"移動速度+5%": {
		"title": "移動速度+5%",
		"description": "§c必要ポイント2",
		"icon": {
			"type": "effect",
			"data": {
				"effect": "minecraft:speed"
			}
		},
		"rewards": [
			{
				"type": "puffish_skills:attribute",
				"data": {
					"attribute": "movement_speed",
					"value": 0.05,
					"operation": "multiply_total"
				}
			}
		],
		"cost": 2,
		"metadata": {
			"icon": "dyugqeljmrnenmll"
		}
	},
	"経験値ボーナス+10%": {
		"title": "経験値ボーナス+10%",
		"description": "§c必要ポイント2",
		"size": 1,
		"icon": {
			"type": "item",
			"data": {
				"item": "minecraft:experience_bottle"
			}
		},
		"frame": {
			"type": "advancement",
			"data": {
				"frame": "task"
			}
		},
		"rewards": [
			{
				"type": "puffish_skills:attribute",
				"data": {
					"attribute": "puffish_attributes:experience",
					"value": 0.1,
					"operation": "multiply_base"
				}
			}
		],
		"cost": 2,
		"metadata": {
			"icon": "k85ez3sdpl3yvggs"
		}
	},
	"スタミナ強化+1.0": {
		"title": "スタミナ強化+1.0",
		"description": "§c必要ポイント1",
		"size": 1,
		"icon": {
			"type": "item",
			"data": {
				"item": "minecraft:sugar"
			}
		},
		"frame": {
			"type": "advancement",
			"data": {
				"frame": "task"
			}
		},
		"rewards": [
			{
				"type": "puffish_skills:attribute",
				"data": {
					"attribute": "puffish_attributes:stamina",
					"value": 1,
					"operation": "addition"
				}
			}
		],
		"cost": 1,
		"metadata": {
			"icon": "70lks4bgwjo160dn"
		}
	},
	"俊敏+5%": {
		"title": "俊敏+5%",
		"description": "§c必要ポイント2",
		"size": 1,
		"icon": {
			"type": "item",
			"data": {
				"item": "minecraft:leather_boots"
			}
		},
		"frame": {
			"type": "advancement",
			"data": {
				"frame": "task"
			}
		},
		"rewards": [
			{
				"type": "puffish_skills:attribute",
				"data": {
					"attribute": "puffish_attributes:sprinting_speed",
					"value": 0.05,
					"operation": "multiply_base"
				}
			}
		],
		"cost": 2,
		"metadata": {
			"icon": "u36nyv524yqubmpd"
		}
	},
	"跳躍力+0.05": {
		"title": "跳躍力+0.05",
		"description": "§c必要ポイント2",
		"size": 1,
		"icon": {
			"type": "effect",
			"data": {
				"effect": "minecraft:jump_boost"
			}
		},
		"frame": {
			"type": "advancement",
			"data": {
				"frame": "task"
			}
		},
		"rewards": [
			{
				"type": "puffish_skills:attribute",
				"data": {
					"attribute": "puffish_attributes:jump",
					"value": 0.05,
					"operation": "addition"
				}
			}
		],
		"cost": 2,
		"metadata": {
			"icon": "azhqj2tq60viv5xb"
		}
	},
	"落下軽減+1.0": {
		"title": "落下軽減+1.0",
		"description": "§c必要ポイント2",
		"size": 1,
		"icon": {
			"type": "effect",
			"data": {
				"effect": "minecraft:levitation"
			}
		},
		"frame": {
			"type": "advancement",
			"data": {
				"frame": "task"
			}
		},
		"rewards": [
			{
				"type": "puffish_skills:attribute",
				"data": {
					"attribute": "puffish_attributes:fall_reduction",
					"value": 1,
					"operation": "addition"
				}
			}
		],
		"cost": 2,
		"metadata": {
			"icon": "ep2tc5qlv5jaxnoq"
		}
	},
	"金床修理コスト-5%": {
		"title": "金床修理コスト-5%",
		"description": "§c必要ポイント3",
		"size": 1,
		"icon": {
			"type": "item",
			"data": {
				"item": "minecraft:anvil"
			}
		},
		"frame": {
			"type": "advancement",
			"data": {
				"frame": "task"
			}
		},
		"rewards": [
			{
				"type": "puffish_skills:attribute",
				"data": {
					"attribute": "puffish_attributes:repair_cost",
					"value": -0.95,
					"operation": "multiply_base"
				}
			}
		],
		"cost": 3,
		"metadata": {
			"icon": "oyqklqfur9a4js8f"
		}
	},
	"ノックバック耐性+10%": {
		"title": "ノックバック耐性+10%",
    "description": "必要ポイント1",
		"icon": {
			"type": "effect",
			"data": {
				"effect": "health_boost"
			}
		},
    "frame": {
			"type": "advancement",
			"data": {
				"frame": "task"
			}
		},
		"rewards": [
      {
        "type": "puffish_skills:attribute",
        "data": {
          "attribute": "minecraft:knockback_resistance",
          "value": 0.1,
          "operation": "addition"
        }
      }
	],
  "cost": 1
  },
  "移動速度+10%": {
		"title": "移動速度+10%",
    "description": "必要ポイント1",
		"icon": {
			"type": "effect",
			"data": {
				"effect": "health_boost"
			}
		},
    "frame": {
			"type": "advancement",
			"data": {
				"frame": "task"
			}
		},
		"rewards": [
      {
        "type": "puffish_skills:attribute",
        "data": {
          "attribute": "minecraft:movement_speed",
          "value": 0.1,
          "operation": "addition"
        }
      }
	  ],
    "cost": 1
  },
  "跳躍力+10%": {
		"title": "跳躍力+10%",
    "description": "必要ポイント1",
		"icon": {
			"type": "effect",
			"data": {
				"effect": "health_boost"
			}
		},
    "frame": {
			"type": "advancement",
			"data": {
				"frame": "task"
			}
		},
		"rewards": [
      {
        "type": "puffish_skills:attribute",
        "data": {
          "attribute": "minecraft:jump_strength",
          "value": 0.1,
          "operation": "addition"
        }
      }
	  ],
    "cost": 1
  },
  "攻撃力+10%": {
		"title": "攻撃力+10%",
    "description": "必要ポイント1",
		"icon": {
			"type": "effect",
			"data": {
				"effect": "health_boost"
			}
		},
    "frame": {
			"type": "advancement",
			"data": {
				"frame": "task"
			}
		},
		"rewards": [
      {
        "type": "puffish_skills:attribute",
        "data": {
          "attribute": "minecraft:attack_damage",
          "value": 0.1,
          "operation": "addition"
        }
      }
	  ],
    "cost": 1
  },
  "ノックバック力+10%": {
		"title": "ノックバック力+10%",
    "description": "必要ポイント1",
		"icon": {
			"type": "effect",
			"data": {
				"effect": "health_boost"
			}
		},
    "frame": {
			"type": "advancement",
			"data": {
				"frame": "task"
			}
		},
		"rewards": [
      {
        "type": "puffish_skills:attribute",
        "data": {
          "attribute": "minecraft:attack_knockback",
          "value": 0.1,
          "operation": "addition"
        }
      }
	],
  "cost": 1
},
"攻撃速度+10%": {
		"title": "攻撃速度+10%",
    "description": "必要ポイント1",
		"icon": {
			"type": "effect",
			"data": {
				"effect": "health_boost"
			}
		},
    "frame": {
			"type": "advancement",
			"data": {
				"frame": "task"
			}
		},
		"rewards": [
      {
        "type": "puffish_skills:attribute",
        "data": {
          "attribute": "minecraft:attack_speed",
          "value": 0.1,
          "operation": "addition"
        }
      }
	  ],
    "cost": 1
  },
  "防具強度+1": {
		"title": "防具強度+1",
    "description": "必要ポイント1",
		"icon": {
			"type": "effect",
			"data": {
				"effect": "health_boost"
			}
		},
    "frame": {
			"type": "advancement",
			"data": {
				"frame": "task"
			}
		},
		"rewards": [
      {
        "type": "puffish_skills:attribute",
        "data": {
          "attribute": "minecraft:armor_toughness",
          "value": 0.1,
          "operation": "addition"
        }
      }
	  ],
    "cost": 1
  },
  "衝撃吸収+10%": {
		"title": "衝撃吸収+10%",
    "description": "必要ポイント1",
		"icon": {
			"type": "effect",
			"data": {
				"effect": "health_boost"
			}
		},
    "frame": {
			"type": "advancement",
			"data": {
				"frame": "task"
			}
		},
		"rewards": [
      {
        "type": "puffish_skills:attribute",
        "data": {
          "attribute": "minecraft:max_absorption",
          "value": 0.1,
          "operation": "addition"
        }
      }
  	],
    "cost": 1
  },
  "大きさ+0.1": {
		"title": "大きさ+0.1",
    "description": "必要ポイント1",
		"icon": {
			"type": "effect",
			"data": {
				"effect": "health_boost"
			}
		},
    "frame": {
			"type": "advancement",
			"data": {
				"frame": "task"
			}
		},
		"rewards": [
      {
        "type": "puffish_skills:attribute",
        "data": {
          "attribute": "minecraft:scale",
          "value": 0.1,
          "operation": "addition"
        }
      }
	  ],
    "cost": 1
  },
  "段差上限+0.1": {
		"title": "段差上限+0.1",
    "description": "必要ポイント1",
		"icon": {
			"type": "effect",
			"data": {
				"effect": "health_boost"
			}
		},
    "frame": {
			"type": "advancement",
			"data": {
				"frame": "task"
			}
		},
		"rewards": [
      {
        "type": "puffish_skills:attribute",
        "data": {
          "attribute": "minecraft:step_height",
          "value": 0.1,
          "operation": "addition"
        }
      }
	  ],
    "cost": 1
  },
  "ブロック操作範囲+0.1": {
		"title": "ブロック操作範囲+0.1",
    "description": "必要ポイント1",
		"icon": {
			"type": "effect",
			"data": {
				"effect": "health_boost"
			}
		},
    "frame": {
			"type": "advancement",
			"data": {
				"frame": "task"
			}
		},
		"rewards": [
      {
        "type": "puffish_skills:attribute",
        "data": {
          "attribute": "minecraft:block_interaction_range",
          "value": 0.1,
          "operation": "addition"
        }
      }
	  ],
    "cost": 1
  },
  "エンティティ操作範囲+0.1": {
		  "title": "エンティティ操作範囲+0.1",
      "description": "必要ポイント1",
  		"icon": {
		  	"type": "effect",
			  "data": {
				  "effect": "health_boost"
			  }
		  },
      "frame": {
			  "type": "advancement",
			  "data": {
				  "frame": "task"
			  }
		  },
		  "rewards": [
        {
          "type": "puffish_skills:attribute",
          "data": {
            "attribute": "minecraft:entity_interaction_range",
           "value": 0.1,
            "operation": "addition"
          }
        }
	  ],
    "cost": 1
  },
  "重力+0.1": {
  	"title": "重力+0.1",
    "description": "必要ポイント1",
		"icon": {
			"type": "effect",
			"data": {
				"effect": "health_boost"
			}
		},
    "frame": {
			"type": "advancement",
			"data": {
				"frame": "task"
			}
		},
		"rewards": [
      {
        "type": "puffish_skills:attribute",
        "data": {
          "attribute": "minecraft:gravity",
          "value": 0.1,
          "operation": "addition"
        }
      }
  	],
    "cost": 1
  },
  "安全落下距離+0.1": {
	  	"title": "安全落下距離+0.1",
      "description": "必要ポイント1",
  		"icon": {
	  		"type": "effect",
		  	"data": {
  				"effect": "health_boost"
	  		}
		  },
      "frame": {
	  		"type": "advancement",
		  	"data": {
			  	"frame": "task"
  			}
	  	},
		  "rewards": [
        {
          "type": "puffish_skills:attribute",
          "data": {
            "attribute": "minecraft:safe_fall_distance",
            "value": 0.1,
            "operation": "addition"
          }
        }
	    ],
      "cost": 1
  },
  "ブロック破壊速度+10%": {
		"title": "ブロック破壊速度+10%",
    "description": "必要ポイント1",
	  "icon": {
		  "type": "effect",
			"data": {
				"effect": "health_boost"
			}
		},
    "frame": {
			"type": "advancement",
			"data": {
				"frame": "task"
			}
		},
		"rewards": [
      {
      "type": "puffish_skills:attribute",
        "data": {
        "attribute": "minecraft:block_break_speed",
        "value": 0.1,
        "operation": "addition"
        }
      }
  	],
    "cost": 1
  },
  "炎上時間+10%": {
		"title": "炎上時間+10%",
    "description": "必要ポイント1",
		"icon": {
			"type": "effect",
			"data": {
				"effect": "health_boost"
			}
		},
    "frame": {
			"type": "advancement",
			"data": {
				"frame": "task"
			}
		},
		"rewards": [
      {
        "type": "puffish_skills:attribute",
        "data": {
          "attribute": "minecraft:burning_time",
          "value": 0.1,
          "operation": "addition"
        }
      }
  	],
    "cost": 1
  },
  "爆発ノックバック耐性+10%": {
		"title": "爆発ノックバック耐性+10%",
    "description": "必要ポイント1",
		"icon": {
			"type": "effect",
			"data": {
				"effect": "health_boost"
			}
		},
    "frame": {
			"type": "advancement",
			"data": {
				"frame": "task"
			}
		},
		"rewards": [
      {
        "type": "puffish_skills:attribute",
        "data": {
          "attribute": "minecraft:explosion_knockback_resistance",
          "value": 0.1,
          "operation": "addition"
        }
      }
	  ],
    "cost": 1
  },
  "採掘効率+10%": {
		"title": "採掘効率+10%",
    "description": "必要ポイント1",
		"icon": {
			"type": "effect",
			"data": {
				"effect": "health_boost"
			}
		},
    "frame": {
			"type": "advancement",
			"data": {
				"frame": "task"
			}
		},
		"rewards": [
      {
        "type": "puffish_skills:attribute",
        "data": {
          "attribute": "minecraft:mining_efficiency",
          "value": 0.1,
          "operation": "addition"
        }
      }
	  ],
    "cost": 1
  },
  "移動効率+10%": {
		"title": "移動効率+10%",
    "description": "必要ポイント1",
		"icon": {
			"type": "effect",
			"data": {
				"effect": "health_boost"
			}
		},
    "frame": {
			"type": "advancement",
			"data": {
				"frame": "task"
			}
		},
		"rewards": [
      {
        "type": "puffish_skills:attribute",
        "data": {
          "attribute": "minecraft:movement_efficiency",
          "value": 0.1,
          "operation": "addition"
        }
      }
	  ],
    "cost": 1
  },
  "酸素ボーナス+10%": {
		"title": "酸素ボーナス+10%",
    "description": "必要ポイント1",
		"icon": {
			"type": "effect",
			"data": {
				"effect": "health_boost"
			}
		},
    "frame": {
			"type": "advancement",
			"data": {
				"frame": "task"
			}
		},
		"rewards": [
      {
        "type": "puffish_skills:attribute",
        "data": {
          "attribute": "minecraft:oxygen_bonus",
          "value": 0.1,
          "operation": "addition"
        }
      }
	  ],
    "cost": 1
  },
  "スニーク速度+10%": {
		"title": "スニーク速度+10%",
    "description": "必要ポイント1",
		"icon": {
			"type": "effect",
			"data": {
				"effect": "health_boost"
			}
		},
    "frame": {
			"type": "advancement",
			"data": {
				"frame": "task"
			}
		},
		"rewards": [
      {
        "type": "puffish_skills:attribute",
        "data": {
          "attribute": "minecraft:sneaking_speed",
          "value": 0.1,
          "operation": "addition"
        }
      }
	  ],
    "cost": 1
  },
  "水中採掘速度+10%": {
		"title": "水中採掘速度+10%",
    "description": "必要ポイント1",
		"icon": {
			"type": "effect",
			"data": {
				"effect": "health_boost"
			}
		},
    "frame": {
			"type": "advancement",
			"data": {
				"frame": "task"
			}
		},
		"rewards": [
      {
        "type": "puffish_skills:attribute",
        "data": {
          "attribute": "minecraft:submerged_mining_speed",
          "value": 0.1,
          "operation": "addition"
        }
      }
	  ],
    "cost": 1
  },
  "なぎ払いダメージ比率+10%": {
		"title": "なぎ払いダメージ比率+10%",
    "description": "必要ポイント1",
		"icon": {
			"type": "effect",
			"data": {
				"effect": "health_boost"
			}
		},
    "frame": {
			"type": "advancement",
			"data": {
				"frame": "task"
			}
		},
		"rewards": [
      {
        "type": "puffish_skills:attribute",
        "data": {
          "attribute": "minecraft:sweeping_damage_ratio",
          "value": 0.1,
          "operation": "addition"
        }
      }
	  ],
    "cost": 1
  },
  "水中移動効率+10%": {
		"title": "水中移動効率+10%",
    "description": "必要ポイント1",
		"icon": {
			"type": "effect",
			"data": {
				"effect": "health_boost"
			}
		},
    "frame": {
			"type": "advancement",
			"data": {
				"frame": "task"
			}
		},
		"rewards": [
      {
        "type": "puffish_skills:attribute",
        "data": {
          "attribute": "minecraft:water_movement_efficiency",
          "value": 0.1,
          "operation": "addition"
        }
      }
	  ],
    "cost": 1
  },

  "ウェイポイント送信距離": {
	  "title": "ウェイポイント送信距離",
    "description": "必要ポイント1",
		"icon": {
			"type": "effect",
			"data": {
				"effect": "health_boost"
			}
		},
    "frame": {
			"type": "advancement",
			"data": {
				"frame": "task"
			}
		},
		"rewards": [
      {
        "type": "puffish_skills:attribute",
        "data": {
          "attribute": "minecraft:waypoint_transmit_range",
          "value": 0.1,
          "operation": "addition"
        }
     }
  ],
  "cost": 1
  },
  "ウェイポイント受信距離": {
		"title": "ウェイポイント受信範囲",
    "description": "必要ポイント1",
		"icon": {
			"type": "effect",
			"data": {
				"effect": "health_boost"
			}
		},
    "frame": {
			"type": "advancement",
			"data": {
				"frame": "task"
			}
		},
		"rewards": [
      {
        "type": "puffish_skills:attribute",
        "data": {
          "attribute": "minecraft:waypoint_receive_range",
          "value": 0.1,
          "operation": "addition"
        }
      }
    ],
    "cost": 1
  },
  "カメラ距離": {
		"title": "カメラ距離",
    "description": "必要ポイント1",
		"icon": {
			"type": "effect",
			"data": {
				"effect": "health_boost"
			}
		},
    "frame": {
			"type": "advancement",
			"data": {
				"frame": "task"
			}
		},
		"rewards": [
      {
        "type": "puffish_skills:attribute",
        "data": {
            "attribute": "minecraft:camera_distance",
            "value": 0.1,
            "operation": "addition"
          }
      }
    ],
    "cost": 1
  }
}